rescape_region/__init__.py
rescape_region/admin.py
rescape_region/apps.py
rescape_region/model_helpers.py
rescape_region/urls.py
rescape_region/helpers/__init__.py
rescape_region/helpers/sankey_helpers.py
rescape_region/management/__init__.py
rescape_region/management/commanda/__init__.py
rescape_region/management/commanda/delete_test_data.py
rescape_region/middleware/__init__.py
rescape_region/middleware/debug_middleware.py
rescape_region/migrations/0001_initial.py
rescape_region/migrations/0002_location_project.py
rescape_region/migrations/0003_project_region.py
rescape_region/migrations/0004_auto_20190204_1423.py
rescape_region/migrations/0005_auto_20190219_1443.py
rescape_region/migrations/0006_settings.py
rescape_region/migrations/0007_auto_20190606_1356.py
rescape_region/migrations/0008_project_user.py
rescape_region/migrations/0009_auto_20190930_1247.py
rescape_region/migrations/0010_resource.py
rescape_region/migrations/0011_resource_key.py
rescape_region/migrations/0012_auto_20200227_1437.py
rescape_region/migrations/0013_auto_20200324_1214.py
rescape_region/migrations/0014_auto_20200415_1616.py
rescape_region/migrations/0015_auto_20200611_1139.py
rescape_region/migrations/0016_auto_20200618_1405.py
rescape_region/migrations/0017_auto_20200618_1458.py
rescape_region/migrations/0018_auto_20200619_0903.py
rescape_region/migrations/0019_auto_20200731_1404.py
rescape_region/migrations/0020_auto_20200803_0817.py
rescape_region/migrations/0021_auto_20200803_0818.py
rescape_region/migrations/0022_auto_20200902_1044.py
rescape_region/migrations/0023_auto_20200909_0951.py
rescape_region/migrations/0024_auto_20201207_1751.py
rescape_region/migrations/0025_alter_settings_data.py
rescape_region/migrations/0026_searchlocation.py
rescape_region/migrations/0027_auto_20210428_0929.py
rescape_region/migrations/0028_auto_20210502_1144.py
rescape_region/migrations/0029_jurisdiction.py
rescape_region/migrations/0030_searchjurisdiction.py
rescape_region-0.2.37.dist-info/LICENSE
rescape_region-0.2.37.dist-info/METADATA
rescape_region-0.2.37.dist-info/WHEEL
rescape_region-0.2.37.dist-info/top_level.txt
rescape_region-0.2.37.dist-info/RECORD
