Metadata-Version: 2.1
Name: rescape-region
Version: 0.2.37
Summary: Geospatial region support for Rescape projects
Home-page: https://github.com/calocan/rescape_region
Author: Andy Likuski
Author-email: andy@likuski.org
License: UNKNOWN
Platform: UNKNOWN
Classifier: Programming Language :: Python :: 3
Classifier: License :: OSI Approved :: MIT License
Classifier: Operating System :: OS Independent
License-File: LICENSE
Requires-Dist: pyramda
Requires-Dist: inflection
Requires-Dist: deepmerge
